CHANGES.rst
CONTRIBUTORS.rst
MANIFEST.in
README.rst
setup.cfg
setup.py
pas/__init__.py
pas.plugins.suisseid.egg-info/PKG-INFO
pas.plugins.suisseid.egg-info/SOURCES.txt
pas.plugins.suisseid.egg-info/dependency_links.txt
pas.plugins.suisseid.egg-info/namespace_packages.txt
pas.plugins.suisseid.egg-info/not-zip-safe
pas.plugins.suisseid.egg-info/requires.txt
pas.plugins.suisseid.egg-info/top_level.txt
pas/plugins/__init__.py
pas/plugins/suisseid/README.rst
pas/plugins/suisseid/__init__.py
pas/plugins/suisseid/client.py
pas/plugins/suisseid/config.py
pas/plugins/suisseid/configure.zcml
pas/plugins/suisseid/ech0113.py
pas/plugins/suisseid/integration.xml
pas/plugins/suisseid/metadata.xml
pas/plugins/suisseid/patches.py
pas/plugins/suisseid/plugin.py
pas/plugins/suisseid/tests/__init__.py
pas/plugins/suisseid/tests/test_authentication.py
pas/plugins/suisseid/tests/test_extraction.py
pas/plugins/suisseid/tests/utils.py
pas/plugins/suisseid/tests/data/metadata.xml
pas/plugins/suisseid/www/.DS_Store
pas/plugins/suisseid/www/editSuisseIDSettings.zpt
pas/plugins/suisseid/www/suisseid.png