Metadata-Version: 1.0
Name: pas.plugins.suisseid
Version: 0.1b3
Summary: suisseID PAS plugin for Zope
Home-page: http://www.seantis.ch
Author: Seantis GmbH
Author-email: info@seantis.ch
License: GPL
Platform: UNKNOWN
Classifier: Environment :: Web Environment
Classifier: Framework :: Zope2
Classifier: License :: OSI Approved :: GNU General Public License (GPL)
Classifier: Operating System :: OS Independent
Classifier: Programming Language :: Python
Classifier: Topic :: System :: Systems Administration :: Authentication/Directory
